bottle_jwt.py
bottle_jwt_version.py
bottle_pyjwt-1.3.7.dist-info/LICENSE.txt
bottle_pyjwt-1.3.7.dist-info/METADATA
bottle_pyjwt-1.3.7.dist-info/WHEEL
bottle_pyjwt-1.3.7.dist-info/top_level.txt
bottle_pyjwt-1.3.7.dist-info/RECORD
