Metadata-Version: 2.1
Name: bottle-pyjwt
Version: 1.3.7
Summary: El plugin de bottle-pyjwt permite usar autentificacion mediante token usando el estandar java jwt
Home-page: UNKNOWN
Author: Lorenzo A. Garcia Calzadilla
Author-email: lorenzogarciacalzadilla@gmail.com
Maintainer: 
Maintainer-email: 
License: MIT
Platform: UNKNOWN
Requires-Dist: bottle
Requires-Dist: pyjwt
